moveread/pipelines/game_correction/__init__.py
moveread/pipelines/game_correction/__init__.pyi
moveread/pipelines/game_correction/_types.py
moveread/pipelines/game_correction/api.py
moveread/pipelines/game_correction/cli.py
moveread/pipelines/game_correction/sdk.py
moveread/pipelines/game_correction/spec.py
moveread/pipelines/game_correction/util/__init__.py
moveread/pipelines/game_correction/util/locks.py
moveread/pipelines/game_correction/util/streams.py
moveread_pipelines_game_correction-0.3.1.dist-info/METADATA
moveread_pipelines_game_correction-0.3.1.dist-info/WHEEL
moveread_pipelines_game_correction-0.3.1.dist-info/entry_points.txt
moveread_pipelines_game_correction-0.3.1.dist-info/top_level.txt
moveread_pipelines_game_correction-0.3.1.dist-info/RECORD
